{
  "main_page_header": "Amet mollit dolorib",
  "main_page_text": "Voluptas minima dolo",
  "main_page_background": "https://pleated-jeans.com/wp-content/uploads/2025/01/funny-fashion-choices-what-new-yorkers-wear.jpg",
  "main_page_products_list": [
    {
      "main_page_product_list": "Qui ut vel iusto qui"
    },
    {
      "main_page_product_list": "Voluptas irure paria"
    },
    {
      "main_page_product_list": "Aliquid sit et eiusm"
    },
    {
      "main_page_product_list": "Nihil ut debitis et "
    }
  ]
}
